imgtoascii/__init__.py
imgtoascii-0.0.2.dist-info/License
imgtoascii-0.0.2.dist-info/METADATA
imgtoascii-0.0.2.dist-info/WHEEL
imgtoascii-0.0.2.dist-info/top_level.txt
imgtoascii-0.0.2.dist-info/RECORD
